aiacd/__init__.py
aiacd/acd_excel_maker.py
aiacd/Excel error.log
aiacd/File_Structure_Error.log
aiacd/Generate.log
aiacd/Local.log
aiacd/main.py
aiacd/nd.py
aiacd/re_tools.py
aiacd/rls_to_acd_transform.py
aiacd/tests/__init__.py
aiacd/tests/acd_test_suit.py
aiacd/tools.py
aiacd-0.1.0.dist-info/WHEEL
aiacd-0.1.0.dist-info/METADATA
aiacd-0.1.0.dist-info/RECORD
