Metadata-Version: 2.1
Name: aiacd
Version: 0.1.0
Summary: 
Author: mjaquier
Author-email: mjaquier@mjaquier.xyz
Requires-Python: >=3.8,<4.0
Classifier: Programming Language :: Python :: 3
Classifier: Programming Language :: Python :: 3.8
Requires-Dist: PySimpleGui (>=4.29.0,<5.0.0)
Requires-Dist: openpyxl (>=3.0.5,<4.0.0)
Requires-Dist: pandas (>=1.1.2,<2.0.0)
Requires-Dist: sortedcollections (>=1.2.1,<2.0.0)
